<?xml version = '1.0' encoding = 'UTF-8'?>
<Diagram class="oracle.dbtools.crest.swingui.relational.DPVRelational" name="Relational_1" id="56C291ED-F759-3B46-72B2-E529E9D40183">
<createdBy>Katherine</createdBy>
<modifiedBy>Katherine</modifiedBy>
<createdTime>2015-11-18 01:40:33 UTC</createdTime>
<autoRoute>false</autoRoute>
<boxInbox>true</boxInbox>
<showLegend>false</showLegend>
<showLabels>false</showLabels>
<showRelAttributes>false</showRelAttributes>
<gridEnabled>false</gridEnabled>
<showGrid>false</showGrid>
<diagramColor>-1</diagramColor>
<display>false</display>
<notation>1</notation>
<objectViews>
<OView class="oracle.dbtools.crest.swingui.relational.TVTable" oid="0CB2C5D5-0A6F-07F6-CC58-E799D7959DB8" otype="Table" vid="9A73D4CA-014D-3B63-DE4B-025A0502A19F">
<hideElementsInCurrentOnly>false</hideElementsInCurrentOnly>
<bounds x="361" y="416" width="170" height="214"/>
</OView>
<OView class="oracle.dbtools.crest.swingui.relational.TVTable" oid="1017520C-C45D-DBA0-43A3-9C74CF61AA1F" otype="Table" vid="3D993095-1D86-3A4F-DFE3-179647B939A2">
<hideElementsInCurrentOnly>false</hideElementsInCurrentOnly>
<bounds x="826" y="142" width="170" height="110"/>
</OView>
<OView class="oracle.dbtools.crest.swingui.relational.TVTable" oid="1066D8E8-9D97-D420-E7FB-E896AD0E2E36" otype="Table" vid="2D987213-646B-CF46-0210-F75888DE5AA5">
<hideElementsInCurrentOnly>false</hideElementsInCurrentOnly>
<bounds x="341" y="6" width="170" height="110"/>
</OView>
<OView class="oracle.dbtools.crest.swingui.relational.TVTable" oid="126CA631-2C88-3EF6-A9AA-BCA2090A6BC7" otype="Table" vid="04475908-4ED2-6074-B1A1-E8613D3F15EE">
<hideElementsInCurrentOnly>false</hideElementsInCurrentOnly>
<bounds x="304" y="130" width="244" height="163"/>
</OView>
<OView class="oracle.dbtools.crest.swingui.relational.TVTable" oid="39606644-38DF-3075-E167-CEAD9CDC2D73" otype="Table" vid="E7EF4EAA-787C-467B-0702-DCEAB8B1B97E">
<hideElementsInCurrentOnly>false</hideElementsInCurrentOnly>
<bounds x="732" y="282" width="133" height="139"/>
</OView>
<OView class="oracle.dbtools.crest.swingui.relational.TVTable" oid="58CF034D-FEA3-8098-E6F3-1FBECC877330" otype="Table" vid="DAA2C634-18DB-67C1-C4B9-82CF57961C87">
<hideElementsInCurrentOnly>false</hideElementsInCurrentOnly>
<bounds x="77" y="487" width="170" height="110"/>
</OView>
<OView class="oracle.dbtools.crest.swingui.relational.TVTable" oid="5C92DCCD-8335-8FCF-5760-E35C4782A652" otype="Table" vid="885CB4A5-606B-6F15-5407-F9EDA467FD59">
<hideElementsInCurrentOnly>false</hideElementsInCurrentOnly>
<bounds x="617" y="164" width="144" height="95"/>
</OView>
<OView class="oracle.dbtools.crest.swingui.relational.TVTable" oid="7FB20016-17AC-965A-50D8-FDE93F54F825" otype="Table" vid="189AE32C-29F5-ADB9-AFA1-B18F344ADC2A">
<hideElementsInCurrentOnly>false</hideElementsInCurrentOnly>
<bounds x="621" y="495" width="170" height="110"/>
</OView>
<OView class="oracle.dbtools.crest.swingui.relational.TVTable" oid="9EFC9C09-F57D-D6F4-BFE5-93DE55B7EFE1" otype="Table" vid="4083A375-C3F1-2CDA-3E76-2A429EC85CED">
<hideElementsInCurrentOnly>false</hideElementsInCurrentOnly>
<bounds x="530" y="307" width="170" height="110"/>
</OView>
<OView class="oracle.dbtools.crest.swingui.relational.TVTable" oid="B5A5DAEA-A56D-A643-B6D4-37B4E081E483" otype="Table" vid="6630755E-21C1-2AE7-4B8D-F778754C249A">
<hideElementsInCurrentOnly>false</hideElementsInCurrentOnly>
<bounds x="57" y="6" width="170" height="110"/>
</OView>
<OView class="oracle.dbtools.crest.swingui.relational.TVTable" oid="B66769C7-B45E-AC12-9223-FE611C75AEDC" otype="Table" vid="73C47A09-53C4-012B-2CD7-0B03CE8D0215">
<hideElementsInCurrentOnly>false</hideElementsInCurrentOnly>
<bounds x="170" y="321" width="170" height="110"/>
</OView>
<OView class="oracle.dbtools.crest.swingui.relational.TVTable" oid="CF1B3D09-62AE-A126-9061-DAD43AC8C7D7" otype="Table" vid="6FB5B89D-9947-73EB-7A67-09F4D24ACA40">
<hideElementsInCurrentOnly>false</hideElementsInCurrentOnly>
<bounds x="640" y="4" width="170" height="110"/>
</OView>
<OView class="oracle.dbtools.crest.swingui.relational.TVTable" oid="D57A5919-79DD-C425-67BE-82AB257338EB" otype="Table" vid="3F2B521E-7B7F-D8EE-5C87-8D7D8CEC5A06">
<hideElementsInCurrentOnly>false</hideElementsInCurrentOnly>
<bounds x="17" y="139" width="219" height="132"/>
</OView>
</objectViews>
<connectors>
<Connector class="oracle.dbtools.crest.swingui.relational.TVFKRelation" oid="0240B231-458E-A158-68F5-51A0C34F5C7E" otype="FKIndexAssociation" vid_source="189AE32C-29F5-ADB9-AFA1-B18F344ADC2A" vid_target="9A73D4CA-014D-3B63-DE4B-025A0502A19F">
<hideElementsInCurrentOnly>false</hideElementsInCurrentOnly>
<lineWidth>1</lineWidth>
<points>
<point x="621" y="550"/>
<point x="531" y="550"/>
</points>
</Connector>
<Connector class="oracle.dbtools.crest.swingui.relational.TVFKRelation" oid="05FC5D97-DA26-F6A0-1455-8254C249D2AF" otype="FKIndexAssociation" vid_source="9A73D4CA-014D-3B63-DE4B-025A0502A19F" vid_target="4083A375-C3F1-2CDA-3E76-2A429EC85CED">
<hideElementsInCurrentOnly>false</hideElementsInCurrentOnly>
<lineWidth>1</lineWidth>
<points>
<point x="531" y="416"/>
<point x="530" y="416"/>
</points>
</Connector>
<Connector class="oracle.dbtools.crest.swingui.relational.TVFKRelation" oid="0FB00D70-4CB6-1E6E-BB7D-B45B02C0D6D6" otype="FKIndexAssociation" vid_source="04475908-4ED2-6074-B1A1-E8613D3F15EE" vid_target="885CB4A5-606B-6F15-5407-F9EDA467FD59">
<hideElementsInCurrentOnly>false</hideElementsInCurrentOnly>
<lineWidth>1</lineWidth>
<points>
<point x="548" y="211"/>
<point x="617" y="211"/>
</points>
</Connector>
<Connector class="oracle.dbtools.crest.swingui.relational.TVFKRelation" oid="130FA1F3-C971-B473-A050-9496917249A0" otype="FKIndexAssociation" vid_source="04475908-4ED2-6074-B1A1-E8613D3F15EE" vid_target="6630755E-21C1-2AE7-4B8D-F778754C249A">
<hideElementsInCurrentOnly>false</hideElementsInCurrentOnly>
<lineWidth>1</lineWidth>
<points>
<point x="304" y="211"/>
<point x="227" y="61"/>
</points>
</Connector>
<Connector class="oracle.dbtools.crest.swingui.relational.TVFKRelation" oid="1641B256-7E4F-E9BF-6D94-505D1E29BFA7" otype="FKIndexAssociation" vid_source="9A73D4CA-014D-3B63-DE4B-025A0502A19F" vid_target="04475908-4ED2-6074-B1A1-E8613D3F15EE">
<hideElementsInCurrentOnly>false</hideElementsInCurrentOnly>
<lineWidth>1</lineWidth>
<points>
<point x="446" y="416"/>
<point x="446" y="293"/>
</points>
</Connector>
<Connector class="oracle.dbtools.crest.swingui.relational.TVFKRelation" oid="18FB3433-5B09-6657-CDF1-0A5DF1F435BF" otype="FKIndexAssociation" vid_source="04475908-4ED2-6074-B1A1-E8613D3F15EE" vid_target="73C47A09-53C4-012B-2CD7-0B03CE8D0215">
<hideElementsInCurrentOnly>false</hideElementsInCurrentOnly>
<lineWidth>1</lineWidth>
<points>
<point x="322" y="293"/>
<point x="322" y="321"/>
</points>
</Connector>
<Connector class="oracle.dbtools.crest.swingui.relational.TVFKRelation" oid="5E801917-3A84-0D8E-3048-C346AEE90163" otype="FKIndexAssociation" vid_source="DAA2C634-18DB-67C1-C4B9-82CF57961C87" vid_target="9A73D4CA-014D-3B63-DE4B-025A0502A19F">
<hideElementsInCurrentOnly>false</hideElementsInCurrentOnly>
<lineWidth>1</lineWidth>
<points>
<point x="247" y="542"/>
<point x="361" y="542"/>
</points>
</Connector>
<Connector class="oracle.dbtools.crest.swingui.relational.TVFKRelation" oid="81C212C2-3489-59CA-AB05-78F5EDCD02D2" otype="FKIndexAssociation" vid_source="2D987213-646B-CF46-0210-F75888DE5AA5" vid_target="04475908-4ED2-6074-B1A1-E8613D3F15EE">
<hideElementsInCurrentOnly>false</hideElementsInCurrentOnly>
<lineWidth>1</lineWidth>
<points>
<point x="426" y="116"/>
<point x="426" y="130"/>
</points>
</Connector>
<Connector class="oracle.dbtools.crest.swingui.relational.TVFKRelation" oid="9155E7FE-E437-2E68-EB87-C88ACFFFE636" otype="FKIndexAssociation" vid_source="04475908-4ED2-6074-B1A1-E8613D3F15EE" vid_target="3F2B521E-7B7F-D8EE-5C87-8D7D8CEC5A06">
<hideElementsInCurrentOnly>false</hideElementsInCurrentOnly>
<lineWidth>1</lineWidth>
<points>
<point x="304" y="195"/>
<point x="236" y="195"/>
</points>
</Connector>
<Connector class="oracle.dbtools.crest.swingui.relational.TVFKRelation" oid="9628AF8B-DAFE-B979-47EF-ECF5B274AB74" otype="FKIndexAssociation" vid_source="3D993095-1D86-3A4F-DFE3-179647B939A2" vid_target="885CB4A5-606B-6F15-5407-F9EDA467FD59">
<hideElementsInCurrentOnly>false</hideElementsInCurrentOnly>
<lineWidth>1</lineWidth>
<points>
<point x="826" y="208"/>
<point x="761" y="208"/>
</points>
</Connector>
<Connector class="oracle.dbtools.crest.swingui.relational.TVFKRelation" oid="E04C2C95-DD38-02AD-10B8-C764FAD90AE5" otype="FKIndexAssociation" vid_source="E7EF4EAA-787C-467B-0702-DCEAB8B1B97E" vid_target="4083A375-C3F1-2CDA-3E76-2A429EC85CED">
<hideElementsInCurrentOnly>false</hideElementsInCurrentOnly>
<lineWidth>1</lineWidth>
<points>
<point x="732" y="372"/>
<point x="700" y="372"/>
</points>
</Connector>
<Connector class="oracle.dbtools.crest.swingui.relational.TVFKRelation" oid="E445BEC8-250D-5138-E52E-454655AD60D8" otype="FKIndexAssociation" vid_source="04475908-4ED2-6074-B1A1-E8613D3F15EE" vid_target="4083A375-C3F1-2CDA-3E76-2A429EC85CED">
<hideElementsInCurrentOnly>false</hideElementsInCurrentOnly>
<lineWidth>1</lineWidth>
<points>
<point x="539" y="293"/>
<point x="539" y="307"/>
</points>
</Connector>
<Connector class="oracle.dbtools.crest.swingui.relational.TVFKRelation" oid="E9576724-0486-DB3E-D63C-D1B00A01C97C" otype="FKIndexAssociation" vid_source="04475908-4ED2-6074-B1A1-E8613D3F15EE" vid_target="6FB5B89D-9947-73EB-7A67-09F4D24ACA40">
<hideElementsInCurrentOnly>false</hideElementsInCurrentOnly>
<lineWidth>1</lineWidth>
<points>
<point x="548" y="211"/>
<point x="640" y="59"/>
</points>
</Connector>
<Connector class="oracle.dbtools.crest.swingui.relational.TVFKRelation" oid="EA31E88A-B466-A79A-6210-0097EF9E9D77" otype="FKIndexAssociation" vid_source="9A73D4CA-014D-3B63-DE4B-025A0502A19F" vid_target="73C47A09-53C4-012B-2CD7-0B03CE8D0215">
<hideElementsInCurrentOnly>false</hideElementsInCurrentOnly>
<lineWidth>1</lineWidth>
<points>
<point x="361" y="423"/>
<point x="340" y="423"/>
</points>
</Connector>
<Connector class="oracle.dbtools.crest.swingui.relational.TVFKRelation" oid="FD978A4A-471B-8CF9-4E00-3A44C165E7A8" otype="FKIndexAssociation" vid_source="9A73D4CA-014D-3B63-DE4B-025A0502A19F" vid_target="3F2B521E-7B7F-D8EE-5C87-8D7D8CEC5A06">
<hideElementsInCurrentOnly>false</hideElementsInCurrentOnly>
<lineWidth>1</lineWidth>
<points>
<point x="361" y="523"/>
<point x="126" y="271"/>
</points>
</Connector>
</connectors>
</Diagram>